{
    "data": {
        "notifications": [
            {
                "id": 29,
                "title": "تهانينا على التسجيل!",
                "description": "نسأل الله أن يبارك لك في علمك وعملك. لقد تم تسجيلك بنجاح في الدورة. نتمنى لك رحلة علمية مليئة بالفائدة والنور. نسأل الله لك التوفيق والسداد.",
                "type": 0,
                "createdAt": "2025-03-17T13:52:12.6254479",
                "isRead": false
            },
            {
                "id": 24,
                "title": "تهانينا على التسجيل!",
                "description": "نسأل الله أن يبارك لك في علمك وعملك. لقد تم تسجيلك بنجاح في الدورة. نتمنى لك رحلة علمية مليئة بالفائدة والنور. نسأل الله لك التوفيق والسداد.",
                "type": 0,
                "createdAt": "2025-03-17T01:27:34.8367857",
                "isRead": false
            },
            {
                "id": 23,
                "title": "تهانينا على التسجيل!",
                "description": "نسأل الله أن يبارك لك في علمك وعملك. لقد تم تسجيلك بنجاح في الدورة. نتمنى لك رحلة علمية مليئة بالفائدة والنور. نسأل الله لك التوفيق والسداد.",
                "type": 0,
                "createdAt": "2025-03-17T01:13:53.4290235",
                "isRead": false
            },
            {
                "id": 22,
                "title": "تهانينا على التسجيل!",
                "description": "نسأل الله أن يبارك لك في علمك وعملك. لقد تم تسجيلك بنجاح في الدورة. نتمنى لك رحلة علمية مليئة بالفائدة والنور. نسأل الله لك التوفيق والسداد.",
                "type": 0,
                "createdAt": "2025-03-17T01:13:50.4699217",
                "isRead": false
            },
            {
                "id": 21,
                "title": "تهانينا على التسجيل!",
                "description": "نسأل الله أن يبارك لك في علمك وعملك. لقد تم تسجيلك بنجاح في الدورة. نتمنى لك رحلة علمية مليئة بالفائدة والنور. نسأل الله لك التوفيق والسداد.",
                "type": 0,
                "createdAt": "2025-03-17T01:13:46.4831043",
                "isRead": false
            },
            {
                "id": 20,
                "title": "تهانينا على التسجيل!",
                "description": "نسأل الله أن يبارك لك في علمك وعملك. لقد تم تسجيلك بنجاح في الدورة. نتمنى لك رحلة علمية مليئة بالفائدة والنور. نسأل الله لك التوفيق والسداد.",
                "type": 0,
                "createdAt": "2025-03-17T00:36:53.3000477",
                "isRead": false
            },
            {
                "id": 19,
                "title": "تهانينا على التسجيل!",
                "description": "نسأل الله أن يبارك لك في علمك وعملك. لقد تم تسجيلك بنجاح في الدورة. نتمنى لك رحلة علمية مليئة بالفائدة والنور. نسأل الله لك التوفيق والسداد.",
                "type": 0,
                "createdAt": "2025-03-17T00:36:52.8086061",
                "isRead": false
            },
            {
                "id": 18,
                "title": "تهانينا على التسجيل!",
                "description": "نسأل الله أن يبارك لك في علمك وعملك. لقد تم تسجيلك بنجاح في الدورة. نتمنى لك رحلة علمية مليئة بالفائدة والنور. نسأل الله لك التوفيق والسداد.",
                "type": 0,
                "createdAt": "2025-03-17T00:36:33.7664975",
                "isRead": false
            },
            {
                "id": 17,
                "title": "تهانينا على التسجيل!",
                "description": "نسأل الله أن يبارك لك في علمك وعملك. لقد تم تسجيلك بنجاح في الدورة. نتمنى لك رحلة علمية مليئة بالفائدة والنور. نسأل الله لك التوفيق والسداد.",
                "type": 0,
                "createdAt": "2025-03-17T00:25:31.118961",
                "isRead": false
            },
            {
                "id": 16,
                "title": "تهانينا على التسجيل!",
                "description": "نسأل الله أن يبارك لك في علمك وعملك. لقد تم تسجيلك بنجاح في الدورة. نتمنى لك رحلة علمية مليئة بالفائدة والنور. نسأل الله لك التوفيق والسداد.",
                "type": 0,
                "createdAt": "2025-03-17T00:25:27.9714342",
                "isRead": false
            },
            {
                "id": 15,
                "title": "تهانينا على التسجيل!",
                "description": "نسأل الله أن يبارك لك في علمك وعملك. لقد تم تسجيلك بنجاح في الدورة. نتمنى لك رحلة علمية مليئة بالفائدة والنور. نسأل الله لك التوفيق والسداد.",
                "type": 0,
                "createdAt": "2025-03-17T00:25:26.3442639",
                "isRead": false
            },
            {
                "id": 14,
                "title": "تهانينا على التسجيل!",
                "description": "نسأل الله أن يبارك لك في علمك وعملك. لقد تم تسجيلك بنجاح في الدورة. نتمنى لك رحلة علمية مليئة بالفائدة والنور. نسأل الله لك التوفيق والسداد.",
                "type": 0,
                "createdAt": "2025-03-17T00:23:42.7967287",
                "isRead": false
            },
            {
                "id": 13,
                "title": "تهانينا على التسجيل!",
                "description": "نسأل الله أن يبارك لك في علمك وعملك. لقد تم تسجيلك بنجاح في الدورة. نتمنى لك رحلة علمية مليئة بالفائدة والنور. نسأل الله لك التوفيق والسداد.",
                "type": 0,
                "createdAt": "2025-03-17T00:22:45.9972666",
                "isRead": false
            },
            {
                "id": 12,
                "title": "تهانينا على التسجيل!",
                "description": "نسأل الله أن يبارك لك في علمك وعملك. لقد تم تسجيلك بنجاح في الدورة. نتمنى لك رحلة علمية مليئة بالفائدة والنور. نسأل الله لك التوفيق والسداد.",
                "type": 0,
                "createdAt": "2025-03-17T00:11:01.9315527",
                "isRead": false
            },
            {
                "id": 11,
                "title": "تهانينا على التسجيل!",
                "description": "نسأل الله أن يبارك لك في علمك وعملك. لقد تم تسجيلك بنجاح في الدورة. نتمنى لك رحلة علمية مليئة بالفائدة والنور. نسأل الله لك التوفيق والسداد.",
                "type": 0,
                "createdAt": "2025-03-16T23:34:09.2633797",
                "isRead": false
            },
            {
                "id": 10,
                "title": "Notification 10",
                "description": "This is the tenth notification.",
                "type": 0,
                "createdAt": "2025-03-16T21:39:24.6139756",
                "isRead": false
            },
            {
                "id": 9,
                "title": "Notification 9",
                "description": "This is the ninth notification.",
                "type": 2,
                "createdAt": "2025-03-16T21:39:24.6139711",
                "isRead": false
            },
            {
                "id": 8,
                "title": "Notification 8",
                "description": "This is the eighth notification.",
                "type": 1,
                "createdAt": "2025-03-16T21:39:24.6139667",
                "isRead": false
            },
            {
                "id": 7,
                "title": "Notification 7",
                "description": "This is the seventh notification.",
                "type": 0,
                "createdAt": "2025-03-16T21:39:24.6139621",
                "isRead": false
            },
            {
                "id": 6,
                "title": "Notification 6",
                "description": "This is the sixth notification.",
                "type": 2,
                "createdAt": "2025-03-16T21:39:24.6139574",
                "isRead": false
            },
            {
                "id": 5,
                "title": "Notification 5",
                "description": "This is the fifth notification.",
                "type": 1,
                "createdAt": "2025-03-16T21:39:24.6139506",
                "isRead": false
            },
            {
                "id": 4,
                "title": "Notification 4",
                "description": "This is the fourth notification.",
                "type": 0,
                "createdAt": "2025-03-16T21:39:24.6139432",
                "isRead": false
            },
            {
                "id": 3,
                "title": "Notification 3",
                "description": "This is the third notification.",
                "type": 2,
                "createdAt": "2025-03-16T21:39:24.613938",
                "isRead": false
            },
            {
                "id": 2,
                "title": "Notification 2",
                "description": "This is the second notification.",
                "type": 1,
                "createdAt": "2025-03-16T21:39:24.6139098",
                "isRead": false
            },
            {
                "id": 1,
                "title": "Notification 1",
                "description": "This is the first notification.",
                "type": 0,
                "createdAt": "2025-03-16T21:39:24.6115308",
                "isRead": false
            }
        ],
        "unreadCount": 25,
        "totalCount": 25
    }
}